airweave/__init__.py
airweave/client.py
airweave/collections/__init__.py
airweave/collections/client.py
airweave/collections/raw_client.py
airweave/collections/types/__init__.py
airweave/collections/types/search_collections_readable_id_search_post_request.py
airweave/collections/types/search_collections_readable_id_search_post_response.py
airweave/core/__init__.py
airweave/core/api_error.py
airweave/core/client_wrapper.py
airweave/core/datetime_utils.py
airweave/core/file.py
airweave/core/force_multipart.py
airweave/core/http_client.py
airweave/core/http_response.py
airweave/core/jsonable_encoder.py
airweave/core/pydantic_utilities.py
airweave/core/query_encoder.py
airweave/core/remove_none_from_dict.py
airweave/core/request_options.py
airweave/core/serialization.py
airweave/environment.py
airweave/errors/__init__.py
airweave/errors/unprocessable_entity_error.py
airweave/py.typed
airweave/source_connections/__init__.py
airweave/source_connections/client.py
airweave/source_connections/raw_client.py
airweave/source_connections/types/__init__.py
airweave/source_connections/types/authentication.py
airweave/sources/__init__.py
airweave/sources/client.py
airweave/sources/raw_client.py
airweave/types/__init__.py
airweave/types/action_check_request.py
airweave/types/action_check_response.py
airweave/types/admin_search_destination.py
airweave/types/admin_sync_info.py
airweave/types/api_key.py
airweave/types/api_key_create.py
airweave/types/auth_provider.py
airweave/types/auth_provider_authentication.py
airweave/types/auth_provider_connection.py
airweave/types/auth_provider_connection_create.py
airweave/types/auth_provider_connection_update.py
airweave/types/authentication_details.py
airweave/types/authentication_method.py
airweave/types/behavior_config.py
airweave/types/billing_period.py
airweave/types/billing_period_status.py
airweave/types/billing_period_usage.py
airweave/types/billing_plan.py
airweave/types/billing_status.py
airweave/types/billing_transition.py
airweave_sdk-0.8.56.dist-info/METADATA
airweave_sdk-0.8.56.dist-info/WHEEL
airweave_sdk-0.8.56.dist-info/RECORD
